[{"re_key":4,"re_fk_user_key":1,"re_desc":"Marla Cumple","re_fecha_start":"0210      ","re_fecha_end":"0210      ","re_hora":"0700      ","re_freq":24,"re_email":"2407939353@txt.att.net                                                                              ","re_message":"Marla Cumple                                                                                                                                          ","re_from":"Jorge Wolff                                       "},{"re_key":5,"re_fk_user_key":1,"re_desc":"Joshua Cumple","re_fecha_start":"0915      ","re_fecha_end":"0915      ","re_hora":"0700      ","re_freq":24,"re_email":"2407939353@txt.att.net                                                                              ","re_message":"Joshua Cumple                                                                                                                                         ","re_from":"Jorge Wolff                                       "},{"re_key":6,"re_fk_user_key":1,"re_desc":"Carlos Cumple","re_fecha_start":"0824      ","re_fecha_end":"0824      ","re_hora":"0700      ","re_freq":24,"re_email":"2407939353@txt.att.net                                                                              ","re_message":"Carlos Cumple                                                                                                                                         ","re_from":"Jorge Wolff                                       "},{"re_key":7,"re_fk_user_key":1,"re_desc":"Ale Cumple","re_fecha_start":"0518      ","re_fecha_end":"0518      ","re_hora":"0700      ","re_freq":24,"re_email":"2407939353@txt.att.net                                                                              ","re_message":"Ale Cumple                                                                                                                                            ","re_from":"Jorge Wolff                                       "},{"re_key":8,"re_fk_user_key":1,"re_desc":"Caleb Cumple","re_fecha_start":"0302      ","re_fecha_end":"0302      ","re_hora":"0700      ","re_freq":24,"re_email":"2407939353@txt.att.net                                                                              ","re_message":"Caleb Cumple                                                                                                                                          ","re_from":"Jorge Wolff                                       "},{"re_key":9,"re_fk_user_key":1,"re_desc":"Bella Cumple","re_fecha_start":"0226      ","re_fecha_end":"0226      ","re_hora":"0700      ","re_freq":24,"re_email":"2407939353@txt.att.net                                                                              ","re_message":"Bella Cumple                                                                                                                                          ","re_from":"Jorge Wolff                                       "},{"re_key":10,"re_fk_user_key":1,"re_desc":"Kennedy Cumple","re_fecha_start":"1112      ","re_fecha_end":"1112      ","re_hora":"0700      ","re_freq":24,"re_email":"2407939353@txt.att.net                                                                              ","re_message":"Kennedy Cumple                                                                                                                                        ","re_from":"Jorge Wolff                                       "},{"re_key":11,"re_fk_user_key":1,"re_desc":"Brian Cumple","re_fecha_start":"0518      ","re_fecha_end":"0518      ","re_hora":"0700      ","re_freq":24,"re_email":"2407939353@txt.att.net                                                                              ","re_message":"Brian Cumple                                                                                                                                          ","re_from":"Jorge Wolff                                       "},{"re_key":12,"re_fk_user_key":1,"re_desc":"Claudia Cumple","re_fecha_start":"1219      ","re_fecha_end":"1219      ","re_hora":"0700      ","re_freq":24,"re_email":"2407939353@txt.att.net                                                                              ","re_message":"Claudia Cumple                                                                                                                                        ","re_from":"Jorge Wolff                                       "},{"re_key":13,"re_fk_user_key":1,"re_desc":"Carly Cumple","re_fecha_start":"0311      ","re_fecha_end":"0311      ","re_hora":"0700      ","re_freq":24,"re_email":"2407939353@txt.att.net                                                                              ","re_message":"Carly Cumple                                                                                                                                          ","re_from":"Jorge Wolff                                       "},{"re_key":14,"re_fk_user_key":1,"re_desc":"Chris Cumple","re_fecha_start":"1213      ","re_fecha_end":"1213      ","re_hora":"0700      ","re_freq":24,"re_email":"2407939353@txt.att.net                                                                              ","re_message":"Chris Cumple                                                                                                                                          ","re_from":"Jorge Wolff                                       "},{"re_key":15,"re_fk_user_key":1,"re_desc":"Liz Cumple","re_fecha_start":"0326      ","re_fecha_end":"0326      ","re_hora":"0700      ","re_freq":24,"re_email":"2407939353@txt.att.net                                                                              ","re_message":"Liz Cumple                                                                                                                                            ","re_from":"Jorge Wolff                                       "},{"re_key":16,"re_fk_user_key":1,"re_desc":"Colin Cumple","re_fecha_start":"0106      ","re_fecha_end":"0106      ","re_hora":"0700      ","re_freq":24,"re_email":"2407939353@txt.att.net                                                                              ","re_message":"Colin Cumple                                                                                                                                          ","re_from":"Jorge Wolff                                       "},{"re_key":17,"re_fk_user_key":1,"re_desc":"David Cumple","re_fecha_start":"0614      ","re_fecha_end":"0614      ","re_hora":"0700      ","re_freq":24,"re_email":"2407939353@txt.att.net                                                                              ","re_message":"David Cumple                                                                                                                                          ","re_from":"Jorge Wolff                                       "},{"re_key":18,"re_fk_user_key":1,"re_desc":"Allie Cumple","re_fecha_start":"0429      ","re_fecha_end":"0429      ","re_hora":"0700      ","re_freq":24,"re_email":"2407939353@txt.att.net                                                                              ","re_message":"Allie Cumple                                                                                                                                          ","re_from":"Jorge Wolff                                       "},{"re_key":19,"re_fk_user_key":1,"re_desc":"Noah Cumple","re_fecha_start":"0801      ","re_fecha_end":"0801      ","re_hora":"0700      ","re_freq":24,"re_email":"2407939353@txt.att.net                                                                              ","re_message":"Noah Cumple                                                                                                                                           ","re_from":"Jorge Wolff                                       "},{"re_key":20,"re_fk_user_key":1,"re_desc":"Johanna Cumple","re_fecha_start":"0103      ","re_fecha_end":"0103      ","re_hora":"0700      ","re_freq":24,"re_email":"2407939353@txt.att.net                                                                              ","re_message":"Johanna Cumple                                                                                                                                        ","re_from":"Jorge Wolff                                       "},{"re_key":21,"re_fk_user_key":1,"re_desc":"Linda Cumple","re_fecha_start":"1115      ","re_fecha_end":"1115      ","re_hora":"0700      ","re_freq":24,"re_email":"2407939353@txt.att.net                                                                              ","re_message":"Linda Cumple                                                                                                                                          ","re_from":"Jorge Wolff                                       "},{"re_key":22,"re_fk_user_key":1,"re_desc":"Adriana Cumple","re_fecha_start":"0803      ","re_fecha_end":"0803      ","re_hora":"0700      ","re_freq":24,"re_email":"2407939353@txt.att.net                                                                              ","re_message":"Adriana Cumple                                                                                                                                        ","re_from":"Jorge Wolff                                       "},{"re_key":23,"re_fk_user_key":1,"re_desc":"Marco Cumple","re_fecha_start":"0619      ","re_fecha_end":"0619      ","re_hora":"0700      ","re_freq":24,"re_email":"2407939353@txt.att.net                                                                              ","re_message":"Marco Cumple                                                                                                                                          ","re_from":"Jorge Wolff                                       "},{"re_key":24,"re_fk_user_key":1,"re_desc":"Brad Cumple","re_fecha_start":"0905      ","re_fecha_end":"0905      ","re_hora":"0700      ","re_freq":24,"re_email":"2407939353@txt.att.net                                                                              ","re_message":"Brad Cumple                                                                                                                                           ","re_from":"Jorge Wolff                                       "},{"re_key":25,"re_fk_user_key":1,"re_desc":"Audriana Cumple","re_fecha_start":"0804      ","re_fecha_end":"0804      ","re_hora":"0700      ","re_freq":24,"re_email":"2407939353@txt.att.net                                                                              ","re_message":"Audriana Cumple                                                                                                                                       ","re_from":"Jorge Wolff                                       "},{"re_key":26,"re_fk_user_key":1,"re_desc":"Mom Cumple","re_fecha_start":"0629      ","re_fecha_end":"0629      ","re_hora":"0700      ","re_freq":24,"re_email":"2407939353@txt.att.net                                                                              ","re_message":"Mom Cumple                                                                                                                                            ","re_from":"Jorge Wolff                                       "},{"re_key":27,"re_fk_user_key":1,"re_desc":"Benji Cumple","re_fecha_start":"0623      ","re_fecha_end":"0623      ","re_hora":"0700      ","re_freq":24,"re_email":"2407939353@txt.att.net                                                                              ","re_message":"benji Cumple                                                                                                                                          ","re_from":"Jorge Wolff                                       "},{"re_key":28,"re_fk_user_key":1,"re_desc":"Lucas Cumple","re_fecha_start":"0607      ","re_fecha_end":"0607      ","re_hora":"0700      ","re_freq":24,"re_email":"2407939353@txt.att.net                                                                              ","re_message":"Lucas Cumple                                                                                                                                          ","re_from":"Jorge Wolff                                       "},{"re_key":29,"re_fk_user_key":1,"re_desc":"Andrew Cumple","re_fecha_start":"0613      ","re_fecha_end":"0613      ","re_hora":"0700      ","re_freq":24,"re_email":"2407939353@txt.att.net                                                                              ","re_message":"Andrew Cumple                                                                                                                                         ","re_from":"Jorge Wolff                                       "},{"re_key":32,"re_fk_user_key":1,"re_desc":"Visita al NIH","re_fecha_start":"0301      ","re_fecha_end":"0302      ","re_hora":"0700      ","re_freq":24,"re_email":"2407509902@txt.att.net                                                                              ","re_message":"Visita al doc el 2 Marzo 8:30                                                                                                                         ","re_from":"Doctor Appt                                       "},{"re_key":33,"re_fk_user_key":1,"re_desc":"Visita al NIH el 2 de Marzo","re_fecha_start":"0215      ","re_fecha_end":"0217      ","re_hora":"0700      ","re_freq":24,"re_email":"2407509902@txt.att.net                                                                              ","re_message":"Visita al NIH el 2 de Marzo                                                                                                                           ","re_from":"Doctor Appt.                                      "},{"re_key":34,"re_fk_user_key":1,"re_desc":"nuevo recordatorio","re_fecha_start":"0101      ","re_fecha_end":"1001      ","re_hora":"0755      ","re_email":"2407939353@txt.att.net                                                                              ","re_message":"Mensaje de prueba                                                                                                                                     ","re_from":"keybyme                                           "}]